jetson/AI.py
jetson/__init__.py
jetson/lists/object.names
jetson/models/Collision_Avoid/.cache
jetson/models/FaceNet/models/3.6/FaceNet.json
jetson/models/FaceNet/weights/.cache
jetson/models/Track_Follow/.cache
jetson/models/trtpose/human_pose.json
jetson/models/yolov4-tiny/plugins/Makefile
jetson/models/yolov4-tiny/plugins/gpu_cc.py
jetson/models/yolov4-tiny/plugins/yolo_layer.cu
jetson/models/yolov4-tiny/plugins/yolo_layer.h
jetson/torch2trt/__init__.py
jetson/torch2trt/dataset.py
jetson/torch2trt/dataset_calibrator.py
jetson/torch2trt/flatten_module.py
jetson/torch2trt/flattener.py
jetson/torch2trt/misc_utils.py
jetson/torch2trt/parse_objects.py
jetson/torch2trt/plugins.py
jetson/torch2trt/torch2trt.py
jetson/torch2trt/trt_module.py
jetson/torch2trt/utils.py
jetson/torch2trt/version_utils.py
jetson/torch2trt/converters/__init__.py
jetson/torch2trt/converters/native_converters.py
jetson/torch2trt/converters/plugin_converters.py
jetson/torch2trt/converters/unimplemented_converters.py
jetson/torch2trt/models/__init__.py
jetson/torch2trt/models/common.py
jetson/torch2trt/models/densenet.py
jetson/torch2trt/models/dla.py
jetson/torch2trt/models/mnasnet.py
jetson/torch2trt/models/resnet.py
jetson/yolo2trt/__init__.py
jetson/yolo2trt/calibrator.py
jetson/yolo2trt/onnx_to_trt.py
jetson/yolo2trt/plugins.py
jetson/yolo2trt/yolo_to_onnx.py
pop_jetson-0.0.9.dist-info/METADATA
pop_jetson-0.0.9.dist-info/WHEEL
pop_jetson-0.0.9.dist-info/top_level.txt
pop_jetson-0.0.9.dist-info/RECORD
