Metadata-Version: 2.1
Name: pop-jetson
Version: 0.0.9
Summary: AIoT AI library for pop
Author: c.h.min
Author-email: lab2@hanback.co.kr
Classifier: Programming Language :: Python :: 3
Classifier: License :: OSI Approved :: MIT License
Classifier: Operating System :: OS Independent
Requires-Python: >=3.6
Requires-Dist: gdown
Requires-Dist: numpy <=1.23.5,>=1.19.5
Requires-Dist: onnx ==1.9.0 ; python_version == "3.6"
Requires-Dist: onnx >=1.12.0 ; python_version == "3.8"
